mcthings_drawing/__init__.py
mcthings_drawing/circle.py
mcthings_drawing/sphere.py
mcthings_drawing-0.0.2.dist-info/LICENSE
mcthings_drawing-0.0.2.dist-info/METADATA
mcthings_drawing-0.0.2.dist-info/WHEEL
mcthings_drawing-0.0.2.dist-info/top_level.txt
mcthings_drawing-0.0.2.dist-info/RECORD
